jimpass/__init__.py
jimpass/cli.py
jimpass/config.py
jimpass/controller.py
jimpass/parser.py
jimpass/util.py
jimpass/managers/__init__.py
jimpass/managers/base.py
jimpass/managers/bitwarden.py
jimpass/managers/lastpass.py
Jimpass-0.0.4.dist-info/AUTHORS
Jimpass-0.0.4.dist-info/LICENSE
Jimpass-0.0.4.dist-info/METADATA
Jimpass-0.0.4.dist-info/WHEEL
Jimpass-0.0.4.dist-info/entry_points.txt
Jimpass-0.0.4.dist-info/pbr.json
Jimpass-0.0.4.dist-info/top_level.txt
Jimpass-0.0.4.dist-info/RECORD
