Metadata-Version: 2.1
Name: Jimpass
Version: 0.0.4
Summary: A universal password manager interface, powered by Rofi
Home-page: https://github.com/remyrd/jimpass
Author: Remy Rojas
Author-email: remy.rojas@pm.me
License: UNKNOWN
Platform: UNKNOWN
Classifier: Operating System :: Unix
Classifier: Programming Language :: Python :: 3
Classifier: License :: OSI Approved :: GNU General Public License v3 (GPLv3)
Requires-Dist: Click
Requires-Dist: Pyaml
Requires-Dist: Parse
Requires-Dist: Deepdiff
